kmprograms_numbers_operation_app/__init__.py
kmprograms_numbers_operation_app/operation/__init__.py
kmprograms_numbers_operation_app/operation/number_operation.py
kmprograms_numbers_operation_app-0.1.0.dist-info/WHEEL
kmprograms_numbers_operation_app-0.1.0.dist-info/METADATA
kmprograms_numbers_operation_app-0.1.0.dist-info/RECORD
