Metadata-Version: 2.1
Name: kmprograms-numbers-operation-app
Version: 0.1.0
Summary: 
Author: Krzysztof
Author-email: programowanie.krzysiek@gmail.com
Requires-Python: >=3.11,<4.0
Classifier: Programming Language :: Python :: 3
Classifier: Programming Language :: Python :: 3.11
Requires-Dist: pytz (>=2022.6,<2023.0)
